[
  {
    "id": 729,
    "name": "English",
    "locale": "en"
  },
  {
    "id": 730,
    "name": "Spanish",
    "locale": "es"
  },
  {
    "id": 731,
    "name": "French",
    "locale": "fr"
  },
  {
    "id": 732,
    "name": "Italian",
    "locale": "it"
  },
  {
    "id": 733,
    "name": "Hindi",
    "locale": "hi"
  },
  {
    "id": 734,
    "name": "Bengali",
    "locale": "bn"
  },
  {
    "id": 735,
    "name": "Dutch",
    "locale": "nl"
  },
  {
    "id": 736,
    "name": "German",
    "locale": "de"
  },
  {
    "id": 737,
    "name": "Russian",
    "locale": "ru"
  },
  {
    "id": 738,
    "name": "Greek",
    "locale": "el"
  },
  {
    "id": 739,
    "name": "Portugese",
    "locale": "pt"
  },
  {
    "id": 740,
    "name": "Mandarin",
    "locale": "zh"
  },
  {
    "id": 741,
    "name": "Other",
    "locale": "other"
  }
]
